ElectronZhongwenWendang/README.md
ElectronZhongwenWendang/__init__.py
ElectronZhongwenWendang/__main__.py
ElectronZhongwenWendang/file.epub
ElectronZhongwenWendang/index.html
ElectronZhongwenWendang/css/__init__.py
ElectronZhongwenWendang/css/annotations.css
ElectronZhongwenWendang/css/main.css
ElectronZhongwenWendang/css/normalize.css
ElectronZhongwenWendang/css/popup.css
ElectronZhongwenWendang/font/__init__.py
ElectronZhongwenWendang/font/fontello.eot
ElectronZhongwenWendang/font/fontello.svg
ElectronZhongwenWendang/font/fontello.ttf
ElectronZhongwenWendang/font/fontello.woff
ElectronZhongwenWendang/img/__init__.py
ElectronZhongwenWendang/img/annotator-glyph-sprite.png
ElectronZhongwenWendang/img/annotator-icon-sprite.png
ElectronZhongwenWendang/img/apple-touch-icon.png
ElectronZhongwenWendang/img/cancelfullscreen.png
ElectronZhongwenWendang/img/close.png
ElectronZhongwenWendang/img/fullscreen.png
ElectronZhongwenWendang/img/loader.gif
ElectronZhongwenWendang/img/menu-icon.png
ElectronZhongwenWendang/img/save.png
ElectronZhongwenWendang/img/saved.png
ElectronZhongwenWendang/img/settings-s.png
ElectronZhongwenWendang/img/settings.png
ElectronZhongwenWendang/img/star.png
ElectronZhongwenWendang/js/__init__.py
ElectronZhongwenWendang/js/epub.js
ElectronZhongwenWendang/js/epub.min.js
ElectronZhongwenWendang/js/epub.min.map
ElectronZhongwenWendang/js/hooks.min.js
ElectronZhongwenWendang/js/hooks.min.map
ElectronZhongwenWendang/js/reader.js
ElectronZhongwenWendang/js/reader.js.map
ElectronZhongwenWendang/js/reader.min.js
ElectronZhongwenWendang/js/reader.min.map
ElectronZhongwenWendang/js/hooks/__init__.py
ElectronZhongwenWendang/js/hooks/extensions/__init__.py
ElectronZhongwenWendang/js/hooks/extensions/highlight.js
ElectronZhongwenWendang/js/libs/__init__.py
ElectronZhongwenWendang/js/libs/jquery.min.js
ElectronZhongwenWendang/js/libs/localforage.min.js
ElectronZhongwenWendang/js/libs/screenfull.js
ElectronZhongwenWendang/js/libs/screenfull.min.js
electron_zhongwen_wendang-2024.3.1.0.dist-info/METADATA
electron_zhongwen_wendang-2024.3.1.0.dist-info/WHEEL
electron_zhongwen_wendang-2024.3.1.0.dist-info/entry_points.txt
electron_zhongwen_wendang-2024.3.1.0.dist-info/top_level.txt
electron_zhongwen_wendang-2024.3.1.0.dist-info/RECORD
